reconcile/__init__.py
reconcile_ai-1.0.3.dist-info/licenses/LICENSE
reconcile_ai-1.0.3.dist-info/METADATA
reconcile_ai-1.0.3.dist-info/WHEEL
reconcile_ai-1.0.3.dist-info/entry_points.txt
reconcile_ai-1.0.3.dist-info/top_level.txt
reconcile_ai-1.0.3.dist-info/RECORD
