Metadata-Version: 2.4
Name: reconcile-ai
Version: 1.0.3
Summary: AI-powered headless merge conflict resolver
Home-page: https://github.com/kailashchanel/reconcile-ai
Author: Kailash Elumalai
Author-email: Kailash Elumalai <ckailash@stanford.edu>
License: Apache-2.0
Project-URL: Homepage, https://github.com/kailashchanel/reconcile-ai
Project-URL: Repository, https://github.com/kailashchanel/reconcile-ai
Project-URL: Issues, https://github.com/kailashchanel/reconcile-ai/issues
Classifier: Development Status :: 4 - Beta
Classifier: Intended Audience :: Developers
Classifier: License :: OSI Approved :: Apache Software License
Classifier: Operating System :: OS Independent
Classifier: Programming Language :: Python :: 3
Classifier: Programming Language :: Python :: 3.8
Classifier: Programming Language :: Python :: 3.9
Classifier: Programming Language :: Python :: 3.10
Classifier: Programming Language :: Python :: 3.11
Classifier: Programming Language :: Python :: 3.12
Classifier: Topic :: Software Development :: Version Control :: Git
Classifier: Topic :: Utilities
Requires-Python: >=3.8
License-File: LICENSE
Requires-Dist: GitPython>=3.1.0
Requires-Dist: openai>=1.0.0
Provides-Extra: yaml
Requires-Dist: PyYAML>=6.0; extra == "yaml"
Provides-Extra: dev
Requires-Dist: pytest>=6.0; extra == "dev"
Requires-Dist: black; extra == "dev"
Requires-Dist: flake8; extra == "dev"
Requires-Dist: mypy; extra == "dev"
Dynamic: license-file
